king_chat/__init__.py
king_chat/client.py
king_chat/server.py
king_chat-0.1.0.dist-info/LICENSE
king_chat-0.1.0.dist-info/METADATA
king_chat-0.1.0.dist-info/WHEEL
king_chat-0.1.0.dist-info/top_level.txt
king_chat-0.1.0.dist-info/RECORD
