Metadata-Version: 2.1
Name: king-chat
Version: 0.1.0
Summary: This is a powerful chat center for all kinds of messages.
Home-page: https://github.com/yingshaoxo/king-chat
Author: yingshaoxo
Author-email: yingshaoxo@gmail.com
License: GPLv3
Platform: UNKNOWN
Classifier: Programming Language :: Python :: 3
Classifier: License :: OSI Approved :: GNU General Public License v3 (GPLv3)
Requires-Dist: twisted
